peakrdl_toolchain.py
peakrdl-1.3.0.dist-info/licenses/LICENSE
peakrdl-1.3.0.dist-info/METADATA
peakrdl-1.3.0.dist-info/WHEEL
peakrdl-1.3.0.dist-info/top_level.txt
peakrdl-1.3.0.dist-info/RECORD
