Metadata-Version: 2.4
Name: peakrdl
Version: 1.3.0
Summary: Toolchain for control/status register automation and code generation.
Author: Alex Mykyta
License: GPLv3
Project-URL: Source, https://github.com/SystemRDL/PeakRDL
Project-URL: Tracker, https://github.com/SystemRDL/PeakRDL/issues
Project-URL: Changelog, https://github.com/SystemRDL/PeakRDL/releases
Project-URL: Documentation, https://peakrdl.readthedocs.io/
Keywords: SystemRDL,PeakRDL,CSR,compiler,tool,registers,generator,C,header,software,Verilog,SystemVerilog,register abstraction layer,FPGA,ASIC
Classifier: Development Status :: 5 - Production/Stable
Classifier: Programming Language :: Python
Classifier: Programming Language :: Python :: 3
Classifier: Programming Language :: Python :: 3 :: Only
Classifier: Intended Audience :: Developers
Classifier: License :: OSI Approved :: GNU General Public License v3 (GPLv3)
Classifier: Operating System :: OS Independent
Classifier: Topic :: Scientific/Engineering :: Electronic Design Automation (EDA)
Requires-Python: >=3.7
License-File: LICENSE
Requires-Dist: peakrdl-cli
Requires-Dist: peakrdl-html<3,>=2.10.1
Requires-Dist: peakrdl-ipxact<4,>=3.4.1
Requires-Dist: peakrdl-regblock<2,>=0.19.0
Requires-Dist: peakrdl-systemrdl<2,>=0.3.0
Requires-Dist: peakrdl-uvm<3,>=2.3.0
Requires-Dist: peakrdl-cheader<2,>=1.0.0
Dynamic: license-file
